lcolamps/__init__.py
lcolamps/__main__.py
lcolamps/actor.py
lcolamps/commands.py
lcolamps/controller.py
lcolamps/etc/lcolamps.yaml
lcolamps/etc/schema.json
sdss_lcolamps-1.0.3.dist-info/LICENSE.md
sdss_lcolamps-1.0.3.dist-info/METADATA
sdss_lcolamps-1.0.3.dist-info/WHEEL
sdss_lcolamps-1.0.3.dist-info/entry_points.txt
sdss_lcolamps-1.0.3.dist-info/RECORD
